trongcalculator/__init__.py
trongcalculator-0.1.dist-info/LICENSE.txt
trongcalculator-0.1.dist-info/METADATA
trongcalculator-0.1.dist-info/WHEEL
trongcalculator-0.1.dist-info/top_level.txt
trongcalculator-0.1.dist-info/RECORD
