Metadata-Version: 2.1
Name: trongcalculator
Version: 0.1
Summary: Calculator
Home-page: UNKNOWN
Author: trong
Author-email: trongnp.nqd@gmail.com
License: UNKNOWN
Platform: UNKNOWN
Classifier: Programming Language :: Python :: 3
Classifier: License :: OSI Approved :: MIT License
Classifier: Operating System :: OS Independent
